copymanga/cbz.py
copymanga/config.py
copymanga/epub.py
copymanga/function.py
copymanga/login.py
copymanga/main.py
copymanga/settings.py
copymanga_downloader-3.5.5.2.dist-info/METADATA
copymanga_downloader-3.5.5.2.dist-info/WHEEL
copymanga_downloader-3.5.5.2.dist-info/entry_points.txt
copymanga_downloader-3.5.5.2.dist-info/licenses/LICENSE
copymanga_downloader-3.5.5.2.dist-info/RECORD
