Metadata-Version: 2.4
Name: copymanga-downloader
Version: 3.5.5.2
Summary: 使用python+copymanga API来下载copymanga(拷贝漫画)中的漫画，支持批量+选话下载和获取您收藏的漫画并下载！
Project-URL: Repository, https://github.com/misaka10843/copymanga-downloader
Project-URL: Issues, https://github.com/misaka10843/copymanga-downloader/issues
Author-email: misaka10843 <misaka10843@outlook.jp>
License:                     GNU GENERAL PUBLIC LICENSE
License-File: LICENSE
Keywords: copymanga,downloader
Classifier: License :: OSI Approved :: GNU General Public License v3 (GPLv3)
Classifier: Operating System :: MacOS
Classifier: Operating System :: Microsoft :: Windows
Classifier: Operating System :: POSIX :: Linux
Classifier: Programming Language :: Python :: 3.10
Classifier: Programming Language :: Python :: 3.11
Classifier: Programming Language :: Python :: 3.12
Classifier: Topic :: Utilities
Requires-Python: >=3.10
Requires-Dist: requests
Requires-Dist: rich
